another_statistic_distributions/Binomialdistribution.py
another_statistic_distributions/Gaussiandistribution.py
another_statistic_distributions/Generaldistribution.py
another_statistic_distributions/__init__.py
another_statistic_distributions-0.0.1.dist-info/LICENSE
another_statistic_distributions-0.0.1.dist-info/METADATA
another_statistic_distributions-0.0.1.dist-info/WHEEL
another_statistic_distributions-0.0.1.dist-info/top_level.txt
another_statistic_distributions-0.0.1.dist-info/RECORD
